cvcreator/__init__.py
cvcreator/__main__.py
cvcreator/aggregate/__init__.py
cvcreator/aggregate/content.py
cvcreator/aggregate/schema.py
cvcreator/compile.py
cvcreator/data/badges/AWS.pdf
cvcreator/data/badges/Amazon S3.pdf
cvcreator/data/badges/Angular.pdf
cvcreator/data/badges/Apache Spark.pdf
cvcreator/data/badges/Apple OS.pdf
cvcreator/data/badges/Azure Databricks.pdf
cvcreator/data/badges/Bash.pdf
cvcreator/data/badges/Boost.pdf
cvcreator/data/badges/C++.pdf
cvcreator/data/badges/CMake.pdf
cvcreator/data/badges/CSS.pdf
cvcreator/data/badges/C\#.pdf
cvcreator/data/badges/CircleCI.pdf
cvcreator/data/badges/Clojure.pdf
cvcreator/data/badges/CodeCov.pdf
cvcreator/data/badges/Confluence.pdf
cvcreator/data/badges/Dash.pdf
cvcreator/data/badges/Django.pdf
cvcreator/data/badges/Docker.pdf
cvcreator/data/badges/Elastic Search.pdf
cvcreator/data/badges/Elixir.pdf
cvcreator/data/badges/Emacs.pdf
cvcreator/data/badges/Erlang.pdf
cvcreator/data/badges/FastAPI.pdf
cvcreator/data/badges/Flask.pdf
cvcreator/data/badges/Fortran.pdf
cvcreator/data/badges/Git.pdf
cvcreator/data/badges/Go.pdf
cvcreator/data/badges/Google Cloud Platform.pdf
cvcreator/data/badges/Grafana.pdf
cvcreator/data/badges/GraphQL.pdf
cvcreator/data/badges/HTML.pdf
cvcreator/data/badges/Heroku.pdf
cvcreator/data/badges/Hugo.pdf
cvcreator/data/badges/Inkscape.pdf
cvcreator/data/badges/JQuery.pdf
cvcreator/data/badges/JUnit.pdf
cvcreator/data/badges/Java.pdf
cvcreator/data/badges/Javascript.pdf
cvcreator/data/badges/JetBrains.pdf
cvcreator/data/badges/Jira.pdf
cvcreator/data/badges/Julia.pdf
cvcreator/data/badges/Jupyter Notebook.pdf
cvcreator/data/badges/Keras.pdf
cvcreator/data/badges/Kubernetes.pdf
cvcreator/data/badges/Linux.pdf
cvcreator/data/badges/Luascript.pdf
cvcreator/data/badges/Markdown.pdf
cvcreator/data/badges/Mathematica.pdf
cvcreator/data/badges/Matlab.pdf
cvcreator/data/badges/Mercurial.pdf
cvcreator/data/badges/Microsoft Azure.pdf
cvcreator/data/badges/Microsoft Excel.pdf
cvcreator-1.1.17.dist-info/METADATA
cvcreator-1.1.17.dist-info/WHEEL
cvcreator-1.1.17.dist-info/entry_points.txt
cvcreator-1.1.17.dist-info/RECORD
