Metadata-Version: 2.1
Name: cvcreator
Version: 1.1.17
Summary: An automated tool for creating CVs on the fly.
License: MIT
Author: Jonathan Feinberg
Author-email: jonathf@gmail.com
Requires-Python: >=3.7
Classifier: License :: OSI Approved :: MIT License
Classifier: Programming Language :: Python :: 3
Classifier: Programming Language :: Python :: 3.7
Classifier: Programming Language :: Python :: 3.8
Classifier: Programming Language :: Python :: 3.9
Classifier: Programming Language :: Python :: 3.10
Classifier: Programming Language :: Python :: 3.11
Requires-Dist: Jinja2 (>=2.11.3,<4.0.0)
Requires-Dist: PyYAML (==5.3.1)
Requires-Dist: click (>=8.0.1,<9.0.0)
Requires-Dist: click-help-colors (>=0.9,<0.10)
Requires-Dist: markupsafe (==2.0.1)
Requires-Dist: pycountry (>=20.7.3,<21.0.0)
Requires-Dist: pydantic (>=1.8.1,<2.0.0)
Requires-Dist: toml (>=0.10.2,<0.11.0)
